atv/__about__.py
atv/__init__.py
atv/__main__.py
atv/app.py
atv/cli.py
atv/processes.py
atv-0.1.2.dist-info/METADATA
atv-0.1.2.dist-info/WHEEL
atv-0.1.2.dist-info/entry_points.txt
atv-0.1.2.dist-info/licenses/LICENSE
atv-0.1.2.dist-info/RECORD
