Metadata-Version: 2.4
Name: atv
Version: 0.1.2
Summary: atv(async task viewer): a TUI tool for experimenting with Python 3.14 asyncio ps/pstree features
Project-URL: Repository, https://github.com/jrfk/atv
License-File: LICENSE
Requires-Python: >=3.14
Requires-Dist: psutil>=5.9
Requires-Dist: textual<0.61,>=0.57
